Metadata-Version: 1.0
Name: gdbd-distributions
Version: 1.2
Summary: Gaussian and Binomial distributions
Home-page: UNKNOWN
Author: Sourabh Rustagi
Author-email: sourabhrustagi1@gmail.com
License: UNKNOWN
Platform: UNKNOWN
